{
  "history": [
    {
      "results": {
        "special": "04935",
        "first": "48080",
        "second": [
          "08360",
          "20873"
        ],
        "third": [
          "14708",
          "23704",
          "12160"
        ],
        "fourth": [
          "37803",
          "21338",
          "95638",
          "57135"
        ],
        "fifth": [
          "90401",
          "29657",
          "53923"
        ],
        "sixth": [
          "30414",
          "94615"
        ],
        "seventh": [
          "63014",
          "93092",
          "42352",
          "86417"
        ]
      },
      "drawTime": 1748924400011,
      "nextDrawTime": 1748924400000
    },
    {
      "results": {
        "special": "41775",
        "first": "06586",
        "second": [
          "99909",
          "39410"
        ],
        "third": [
          "37640",
          "77592",
          "27234"
        ],
        "fourth": [
          "42311",
          "64189",
          "22343",
          "36469"
        ],
        "fifth": [
          "96180",
          "70806",
          "60550"
        ],
        "sixth": [
          "12357",
          "46025"
        ],
        "seventh": [
          "06558",
          "12044",
          "41395",
          "75538"
        ]
      },
      "drawTime": 1748923800017,
      "nextDrawTime": 1748923800000
    },
    {
      "results": {
        "special": "61886",
        "first": "41809",
        "second": [
          "11768",
          "60122"
        ],
        "third": [
          "66281",
          "74280",
          "41326"
        ],
        "fourth": [
          "92054",
          "97422",
          "59004",
          "30478"
        ],
        "fifth": [
          "24546",
          "03833",
          "43734"
        ],
        "sixth": [
          "40432",
          "28420"
        ],
        "seventh": [
          "43504",
          "34261",
          "98972",
          "90806"
        ]
      },
      "drawTime": 1748923200016,
      "nextDrawTime": 1748923200000
    },
    {
      "results": {
        "special": "44552",
        "first": "50242",
        "second": [
          "81586",
          "69941"
        ],
        "third": [
          "30031",
          "69483",
          "55229"
        ],
        "fourth": [
          "00434",
          "51103",
          "02100",
          "49126"
        ],
        "fifth": [
          "12031",
          "23463",
          "59474"
        ],
        "sixth": [
          "40574",
          "59657"
        ],
        "seventh": [
          "89670",
          "35777",
          "30432",
          "13799"
        ]
      },
      "drawTime": 1748922600015,
      "nextDrawTime": 1748922600000
    },
    {
      "results": {
        "special": "11964",
        "first": "68144",
        "second": [
          "58840",
          "99631"
        ],
        "third": [
          "95255",
          "02248",
          "49239"
        ],
        "fourth": [
          "92859",
          "86906",
          "17520",
          "39565"
        ],
        "fifth": [
          "08602",
          "49480",
          "07703"
        ],
        "sixth": [
          "47152",
          "21572"
        ],
        "seventh": [
          "68208",
          "76715",
          "01667",
          "76927"
        ]
      },
      "drawTime": 1748922000017,
      "nextDrawTime": 1748922000000
    },
    {
      "results": {
        "special": "13457",
        "first": "20785",
        "second": [
          "96007",
          "93102"
        ],
        "third": [
          "55142",
          "72038",
          "58507"
        ],
        "fourth": [
          "59532",
          "07049",
          "85243",
          "19646"
        ],
        "fifth": [
          "54482",
          "03474",
          "45941"
        ],
        "sixth": [
          "54725",
          "24010"
        ],
        "seventh": [
          "59374",
          "18063",
          "67648",
          "94092"
        ]
      },
      "drawTime": 1748921400015,
      "nextDrawTime": 1748921400000
    },
    {
      "results": {
        "special": "67383",
        "first": "32006",
        "second": [
          "92838",
          "10923"
        ],
        "third": [
          "40006",
          "02265",
          "63813"
        ],
        "fourth": [
          "87549",
          "10527",
          "01369",
          "96371"
        ],
        "fifth": [
          "63945",
          "68457",
          "13891"
        ],
        "sixth": [
          "65766",
          "09669"
        ],
        "seventh": [
          "93836",
          "91091",
          "26242",
          "36923"
        ]
      },
      "drawTime": 1748920800047,
      "nextDrawTime": 1748920800000
    },
    {
      "results": {
        "special": "20797",
        "first": "15913",
        "second": [
          "25291",
          "73677"
        ],
        "third": [
          "74991",
          "84261",
          "83583"
        ],
        "fourth": [
          "79127",
          "13216",
          "90222",
          "27881"
        ],
        "fifth": [
          "46759",
          "68912",
          "32349"
        ],
        "sixth": [
          "61189",
          "07584"
        ],
        "seventh": [
          "85019",
          "78982",
          "29986",
          "72502"
        ]
      },
      "drawTime": 1748920200018,
      "nextDrawTime": 1748920200000
    },
    {
      "results": {
        "special": "91565",
        "first": "57403",
        "second": [
          "77390",
          "75367"
        ],
        "third": [
          "29422",
          "84545",
          "54195"
        ],
        "fourth": [
          "62270",
          "67167",
          "81699",
          "69650"
        ],
        "fifth": [
          "93729",
          "17382",
          "44408"
        ],
        "sixth": [
          "90207",
          "29834"
        ],
        "seventh": [
          "63571",
          "21235",
          "64421",
          "83530"
        ]
      },
      "drawTime": 1748919600015,
      "nextDrawTime": 1748919600000
    },
    {
      "results": {
        "special": "13179",
        "first": "81051",
        "second": [
          "83631",
          "23564"
        ],
        "third": [
          "95379",
          "41388",
          "71556"
        ],
        "fourth": [
          "20805",
          "13844",
          "73902",
          "26438"
        ],
        "fifth": [
          "37921",
          "87087",
          "89023"
        ],
        "sixth": [
          "56786",
          "53338"
        ],
        "seventh": [
          "43090",
          "84845",
          "82735",
          "92543"
        ]
      },
      "drawTime": 1748919000016,
      "nextDrawTime": 1748919000000
    }
  ],
  "lastUpdate": 1748924400011,
  "nextScheduledDraw": 1748924400000
}