{
  "100053970942155": {
    "progress": {
      "work": 2
    },
    "completed": {},
    "lastReset": "Sun Mar 16 2025",
    "lastRewardClaim": null
  },
  "100055417691992": {
    "progress": {
      "work": 1
    },
    "completed": {},
    "lastReset": "Sun Mar 16 2025",
    "lastRewardClaim": null
  },
  "61565429063061": {
    "progress": {
      "work": 1
    },
    "completed": {},
    "lastReset": "Sun Mar 16 2025",
    "lastRewardClaim": null
  },
  "100076957299243": {
    "progress": {
      "work": 1
    },
    "completed": {},
    "lastReset": "Sun Mar 16 2025",
    "lastRewardClaim": null
  },
  "100080964828004": {
    "progress": {
      "work": 1
    },
    "completed": {},
    "lastReset": "Mon Mar 17 2025",
    "lastRewardClaim": null
  },
  "61558946907944": {
    "progress": {
      "work": 1,
      "play_games": 1
    },
    "completed": {},
    "lastReset": "Mon Mar 17 2025",
    "lastRewardClaim": null
  },
  "100089981373051": {
    "progress": {
      "work": 4
    },
    "completed": {},
    "lastReset": "Mon Mar 17 2025",
    "lastRewardClaim": null
  },
  "100046632541720": {
    "progress": {
      "play_games": 1
    },
    "completed": {},
    "lastReset": "Mon Mar 17 2025",
    "lastRewardClaim": null
  },
  "100058320200877": {
    "progress": {
      "work": 2
    },
    "completed": {},
    "lastReset": "Mon Mar 17 2025",
    "lastRewardClaim": null
  },
  "61566378911878": {
    "progress": {
      "work": 1
    },
    "completed": {},
    "lastReset": "Mon Mar 17 2025",
    "lastRewardClaim": null
  },
  "100008297661441": {
    "progress": {
      "work": 1
    },
    "completed": {},
    "lastReset": "Mon Mar 17 2025",
    "lastRewardClaim": null
  },
  "61561277064921": {
    "progress": {
      "work": 1
    },
    "completed": {},
    "lastReset": "Mon Mar 17 2025",
    "lastRewardClaim": null
  },
  "100072567218546": {
    "progress": {
      "work": 1
    },
    "completed": {},
    "lastReset": "Mon Mar 17 2025",
    "lastRewardClaim": null
  },
  "61573075153597": {
    "progress": {
      "play_games": 1
    },
    "completed": {},
    "lastReset": "Mon Mar 17 2025",
    "lastRewardClaim": null
  },
  "61573427362389": {
    "progress": {},
    "completed": {},
    "lastReset": "Mon Mar 17 2025",
    "lastRewardClaim": null
  }
}ardClaim": null
  }
}